favorites_icons/__init__.py
favorites_icons/management/__init__.py
favorites_icons/management/commands/__init__.py
favorites_icons/management/commands/generate-icons.py
favorites_icons/templates/favorites-icons-meta.html
favorites_icons/templatetags/__init__.py
favorites_icons/templatetags/favorites_icons.py
favorites_icons/templatetags/utils.py
favorites_icons-1.0.7.dist-info/LICENSE
favorites_icons-1.0.7.dist-info/METADATA
favorites_icons-1.0.7.dist-info/WHEEL
favorites_icons-1.0.7.dist-info/top_level.txt
favorites_icons-1.0.7.dist-info/RECORD
