Metadata-Version: 2.1
Name: favorites-icons
Version: 1.0.7
Summary: Automatic generator for favorites and touch icons, and their appropriate tags.
Home-page: https://github.com/avryhof/favorites_icons
Author: Amos Vryhof
Author-email: amos@vryhofresearch.com
License: MIT
Platform: UNKNOWN
Classifier: Development Status :: 5 - Production/Stable
Classifier: Intended Audience :: Developers
Classifier: License :: OSI Approved :: MIT License
Classifier: Programming Language :: Python :: 3
Requires-Dist: django
